typerx/__init__.py
typerx/_version.py
typerx-0.1.5.dist-info/METADATA
typerx-0.1.5.dist-info/WHEEL
typerx-0.1.5.dist-info/licenses/LICENSE
typerx-0.1.5.dist-info/RECORD
