Metadata-Version: 2.3
Name: typerx
Version: 0.1.5
Summary: A Typer extension for building complex CLI applications, with dataclass support.
Author-email: sagewe <sagewe@fastmail.com>
License: MIT
License-File: LICENSE
Requires-Python: >=3.10
Requires-Dist: pydantic
Requires-Dist: typer
